ChangeLog
LICENSE
MANIFEST.in
README.txt
setup.py
django_siteuser.egg-info/PKG-INFO
django_siteuser.egg-info/SOURCES.txt
django_siteuser.egg-info/dependency_links.txt
django_siteuser.egg-info/requires.txt
django_siteuser.egg-info/top_level.txt
example/manage.py
example/app/__init__.py
example/app/models.py
example/app/siteuser_custom.py
example/app/tests.py
example/app/urls.py
example/app/views.py
example/app/static/jquery-1.9.0.min.js
example/app/static/bootstrap/css/bootstrap.min.css
example/app/static/bootstrap/img/glyphicons-halflings-white.png
example/app/static/bootstrap/img/glyphicons-halflings.png
example/app/static/bootstrap/js/bootstrap.min.js
example/app/templates/account_settings.html
example/app/templates/base.html
example/app/templates/change_password.html
example/app/templates/home.html
example/app/templates/login.html
example/app/templates/notify.html
example/app/templates/register.html
example/app/templates/reset_password.html
example/example/__init__.py
example/example/local_settings.py.example
example/example/settings.py
example/example/urls.py
example/example/wsgi.py
siteuser/__init__.py
siteuser/context_processors.py
siteuser/decorators.py
siteuser/middleware.py
siteuser/settings.py
siteuser/urls.py
siteuser/functional/__init__.py
siteuser/functional/mail.py
siteuser/notify/__init__.py
siteuser/notify/models.py
siteuser/notify/tests.py
siteuser/notify/urls.py
siteuser/notify/views.py
siteuser/templates/siteuser/base.html
siteuser/templates/siteuser/change_password.html
siteuser/templates/siteuser/login.html
siteuser/templates/siteuser/notify.html
siteuser/templates/siteuser/register.html
siteuser/templates/siteuser/reset_password.html
siteuser/templates/siteuser/reset_password_email.html
siteuser/templates/siteuser/upload_avatar.html
siteuser/upload_avatar/__init__.py
siteuser/upload_avatar/models.py
siteuser/upload_avatar/signals.py
siteuser/upload_avatar/tests.py
siteuser/upload_avatar/urls.py
siteuser/upload_avatar/views.py
siteuser/upload_avatar/static/imgareaselect/jquery.imgareaselect.min.js
siteuser/upload_avatar/static/imgareaselect/css/border-anim-h.gif
siteuser/upload_avatar/static/imgareaselect/css/border-anim-v.gif
