Metadata-Version: 1.1
Name: django-siteuser
Version: 0.1.0
Summary: A Django APP for Universal Maintain Accounts
Home-page: https://github.com/yueyoum/django-siteuser
Author: Wang Chao
Author-email: yueyoum@gmail.com
License: BSD
Keywords: django,account,login,register,social,avatar
Platform: UNKNOWN
Classifier: Development Status :: 4 - Beta
Classifier: Topic :: Internet
Classifier: License :: OSI Approved :: BSD License
Classifier: Operating System :: OS Independent
Classifier: Programming Language :: Python
